{
  "bundleSize": null,
  "buildTime": null,
  "webVitals": {
    "fcp": 1867.1386880004497,
    "lcp": 3239.5973255198915,
    "fid": 125.3088620619371,
    "cls": 0.022764377994196817,
    "ttfb": 377.47894682025355,
    "timestamp": 1759591794916
  },
  "system": {
    "platform": "darwin",
    "arch": "arm64",
    "nodeVersion": "v22.18.0",
    "memoryUsage": {
      "rss": 34832384,
      "heapTotal": 5373952,
      "heapUsed": 4512240,
      "external": 1600241,
      "arrayBuffers": 12417
    },
    "uptime": 23.5792745,
    "timestamp": 1759591794916
  },
  "apiPerformance": {
    "averageResponseTime": 237.67871415580882,
    "successRate": 96.69453903136709,
    "errorRate": 1.8434634330289108,
    "totalRequests": 970,
    "timestamp": 1759591794916
  },
  "lastUpdated": "2025-10-04T15:29:54.916Z"
}
