{
  "comparison": {
    "date1": "2025-10-06",
    "date2": "2025-10-07",
    "generatedAt": "2025-10-07T12:25:50.875Z"
  },
  "summary": {
    "totalComparisons": 4,
    "improvements": 3,
    "degradations": 5,
    "neutral": 5
  },
  "details": {
    "bundle": {
      "firstLoadJS": {
        "old": 102,
        "new": 102,
        "change": 0,
        "trend": "decrease"
      },
      "totalBundleSize": {
        "old": 1295,
        "new": 1293,
        "change": -0.15444015444015444,
        "trend": "decrease"
      },
      "fileCount": {
        "old": 29,
        "new": 29,
        "change": 0,
        "trend": "decrease"
      }
    },
    "buildTime": {
      "buildTime": {
        "old": 15620,
        "new": 15409,
        "change": -1.3508322663252241,
        "trend": "decrease"
      }
    },
    "webVitals": {
      "fcp": {
        "old": 1913.0307266561392,
        "new": 1319.5289378338416,
        "change": -31.024163938009636,
        "trend": "improvement"
      },
      "lcp": {
        "old": 3787.1022174119526,
        "new": 2695.8927074317753,
        "change": -28.813838321108033,
        "trend": "improvement"
      },
      "fid": {
        "old": 115.14574369375876,
        "new": 137.5948152892277,
        "change": 19.496223547067817,
        "trend": "degradation"
      },
      "cls": {
        "old": 0.017539981428190844,
        "new": 0.018245073060071993,
        "change": 4.019910937578889,
        "trend": "degradation"
      },
      "ttfb": {
        "old": 565.346800808836,
        "new": 325.70956694828203,
        "change": -42.387651883358565,
        "trend": "improvement"
      }
    },
    "api": {
      "averageResponseTime": {
        "old": 106.49227198685489,
        "new": 129.83630381964377,
        "change": 21.920869371319647,
        "trend": "degradation"
      },
      "successRate": {
        "old": 99.5579584551122,
        "new": 97.67446215849552,
        "change": -1.8918590998085782,
        "trend": "degradation"
      },
      "errorRate": {
        "old": 0.6035401041801318,
        "new": 1.3428134967086867,
        "change": 122.4895226362476,
        "trend": "degradation"
      },
      "totalRequests": {
        "old": 1054,
        "new": 1387,
        "change": 31.59392789373814,
        "trend": "increase"
      }
    }
  }
}
